{
    "name": "PaymentMethods",
    "fields": [
        {
            "fieldName": "paymentMethodName",
            "fieldType": "String",
            "fieldValidateRules": [
                "required"
            ]
        },
        {
            "fieldName": "activeInd",
            "fieldType": "Boolean",
            "fieldValidateRules": [
                "required"
            ]
        },
        {
            "fieldName": "validFrom",
            "fieldType": "LocalDate",
            "fieldValidateRules": [
                "required"
            ]
        },
        {
            "fieldName": "validTo",
            "fieldType": "LocalDate",
            "fieldValidateRules": [
                "required"
            ]
        }
    ],
    "relationships": [],
    "changelogDate": "20190801044916",
    "entityTableName": "payment_methods",
    "dto": "mapstruct",
    "pagination": "no",
    "service": "serviceImpl",
    "jpaMetamodelFiltering": false,
    "fluentMethods": true,
    "clientRootFolder": "",
    "applications": "*",
    "enableEntityAudit": true
}
